{
  "tweet1": {
    "id": "15884570210",
    "author": "@test",
    "avatar": "https://pbs.twimg.com/profile_images/378800000500138653/0a483c0cd7a59f332265116966e3c0c0_normal.jpeg",
    "postedAt": "2010-01-10 19:58:00.000 -0300",
    "isAReply": true,
    "content": "ahora quieren normalizar tomar merca tambien",
    "images": [
      "https://pbs.twimg.com/media/ER9pESAWsAA_wlK?format=jpg&name=small",
      "https://pbs.twimg.com/media/ER9pESAWsAA_wlK?format=jpg&name=small",
      "https://pbs.twimg.com/media/Fl46QBfWYAIWBB_?format=jpg&name=small",
      "https://pbs.twimg.com/media/Fl46QBfWYAIWBB_?format=jpg&name=small",
      "https://pbs.twimg.com/media/Fl46QBfWYAIWBB_?format=jpg&name=small",
      "https://pbs.twimg.com/media/ER9pESAWsAA_wlK?format=jpg&name=small",
      "https://pbs.twimg.com/media/Fl46QBfWYAIWBB_?format=jpg&name=small",
      "https://pbs.twimg.com/media/Fl46QBfWYAIWBB_?format=jpg&name=small",
      "https://pbs.twimg.com/media/Fl46QBfWYAIWBB_?format=jpg&name=small",
      "https://pbs.twimg.com/media/ER9pESAWsAA_wlK?format=jpg&name=small",
      "https://pbs.twimg.com/media/Fl46QBfWYAIWBB_?format=jpg&name=small",
      "https://pbs.twimg.com/media/Fl46QBfWYAIWBB_?format=jpg&name=small",
      "https://pbs.twimg.com/media/Fl46QBfWYAIWBB_?format=jpg&name=small"],
    "quote": {
      "author": "@quoted",
      "avatar": "https://pbs.twimg.com/profile_images/1691975017137844224/SAtywYGF_mini.jpg",
      "postedAt": "2016-07-13 20:48:52.000 -0300",
      "isAReply": true,
      "content": "Todos miran la moneda menos Maradona, que mira al capitán rival. ¿Cómo no vas a salir campeón?",
      "images": ["https://pbs.twimg.com/media/ER9pESAWsAA_wlK?format=jpg&name=small", "https://pbs.twimg.com/media/ER9pESAWsAA_wlK?format=jpg&name=small", "https://pbs.twimg.com/media/ER9pESAWsAA_wlK?format=jpg&name=small", "https://pbs.twimg.com/media/ER9pESAWsAA_wlK?format=jpg&name=small"]
    }
  },
  "tweet2": {
    "id": "15884570210",
    "author": "@test",
    "avatar": "https://pbs.twimg.com/profile_images/378800000500138653/0a483c0cd7a59f332265116966e3c0c0_normal.jpeg",
    "posted_at": "2010-06-10 19:58:00.000 -0300",
    "isAReply": false,
    "content": "Vamos a tomar una linea — Tomar\uD83E\uDD14 https://t/438317775?1524990439…",
    "images": ["https://pbs.twimg.com/media/DnP4OjKWwAAZCJv?format=jpg&name=small"]
  },
  "tweet3": {
    "id": "15884570210",
    "author": "@test",
    "avatar": "https://pbs.twimg.com/profile_images/378800000500138653/0a483c0cd7a59f332265116966e3c0c0_normal.jpeg",
    "posted_at": "2010-06-10 19:58:00.000 -0300",
    "isAReply": true,
    "content": "#PorElTarifazoTuveQue acordarme qué colectivo tomé, para tomar una línea distinta y que la @SUBE me haga el descuento.",
    "images": []
  },
  "tweet4": {
    "id": "15884570210",
    "author": "@test",
    "avatar": "https://pbs.twimg.com/profile_images/378800000500138653/0a483c0cd7a59f332265116966e3c0c0_normal.jpeg",
    "posted_at": "2010-06-10 19:58:00.000 -0300",
    "isAReply": false,
    "content": "ahora quieren normalizar tomar merca tambien",
    "images": [
      "https://pbs.twimg.com/media/ER9pESAWsAA_wlK?format=jpg&name=small",
      "https://pbs.twimg.com/media/ER9pESAWsAA_wlK?format=jpg&name=small",
      "https://pbs.twimg.com/media/Fl46QBfWYAIWBB_?format=jpg&name=small",
      "https://pbs.twimg.com/media/Fl46QBfWYAIWBB_?format=jpg&name=small"],
    "quote": {
      "author": "@quoted",
      "avatar": "https://pbs.twimg.com/profile_images/1691975017137844224/SAtywYGF_mini.jpg",
      "postedAt": "2016-07-13 20:48:52.000 -0300",
      "isAReply": false,
      "content": "Todos miran la moneda menos Maradona, que mira al capitán rival. ¿Cómo no vas a salir campeón?",
      "images": ["https://pbs.twimg.com/media/ER9pESAWsAA_wlK?format=jpg&name=small", "https://pbs.twimg.com/media/ER9pESAWsAA_wlK?format=jpg&name=small"]
    }
  }
}